LHCbWebDIRAC/__init__.py
LHCbWebDIRAC/WebApp/__init__.py
LHCbWebDIRAC/WebApp/web.cfg
LHCbWebDIRAC/WebApp/CompileTeplates/lhcb_appAcounting.tpl
LHCbWebDIRAC/WebApp/CompileTeplates/lhcb_appBookkeepingBrowser.tpl
LHCbWebDIRAC/WebApp/CompileTeplates/lhcb_appBookkeepingSimDescription.tpl
LHCbWebDIRAC/WebApp/CompileTeplates/lhcb_appJobMonitor.tpl
LHCbWebDIRAC/WebApp/CompileTeplates/lhcb_appPilotMonitor.tpl
LHCbWebDIRAC/WebApp/CompileTeplates/lhcb_appPilotSummary.tpl
LHCbWebDIRAC/WebApp/CompileTeplates/lhcb_appTransformationMonitor.tpl
LHCbWebDIRAC/WebApp/handler/AccountingHandler.py
LHCbWebDIRAC/WebApp/handler/BookkeepingBrowserHandler.py
LHCbWebDIRAC/WebApp/handler/BookkeepingSimDescriptionHandler.py
LHCbWebDIRAC/WebApp/handler/DowntimesHandler.py
LHCbWebDIRAC/WebApp/handler/LHCbJobMonitorHandler.py
LHCbWebDIRAC/WebApp/handler/LHCbPilotMonitorHandler.py
LHCbWebDIRAC/WebApp/handler/LHCbPilotSummaryHandler.py
LHCbWebDIRAC/WebApp/handler/LHCbStepManagerHandler.py
LHCbWebDIRAC/WebApp/handler/LHCbTransformationMonitorHandler.py
LHCbWebDIRAC/WebApp/handler/ProductionLib.py
LHCbWebDIRAC/WebApp/handler/ProductionRequestManagerHandler.py
LHCbWebDIRAC/WebApp/handler/RAWIntegrityMonitorHandler.py
LHCbWebDIRAC/WebApp/handler/__init__.py
LHCbWebDIRAC/WebApp/static/LHCbDIRAC/Accounting/build/Accounting.js
LHCbWebDIRAC/WebApp/static/LHCbDIRAC/Accounting/build/Accounting.js.gz
LHCbWebDIRAC/WebApp/static/LHCbDIRAC/Accounting/build/index.html
LHCbWebDIRAC/WebApp/static/LHCbDIRAC/Accounting/build/index.html.gz
LHCbWebDIRAC/WebApp/static/LHCbDIRAC/Accounting/classes/Accounting.js
LHCbWebDIRAC/WebApp/static/LHCbDIRAC/Accounting/classes/Accounting.js.gz
LHCbWebDIRAC/WebApp/static/LHCbDIRAC/Accounting/css/Accounting.css
LHCbWebDIRAC/WebApp/static/LHCbDIRAC/Accounting/css/Accounting.css.gz
LHCbWebDIRAC/WebApp/static/LHCbDIRAC/BookkeepingBrowser/build/BookkeepingBrowser.js
LHCbWebDIRAC/WebApp/static/LHCbDIRAC/BookkeepingBrowser/build/BookkeepingBrowser.js.gz
LHCbWebDIRAC-6.0.10.dist-info/LICENSE
LHCbWebDIRAC-6.0.10.dist-info/METADATA
LHCbWebDIRAC-6.0.10.dist-info/WHEEL
LHCbWebDIRAC-6.0.10.dist-info/entry_points.txt
LHCbWebDIRAC-6.0.10.dist-info/top_level.txt
LHCbWebDIRAC-6.0.10.dist-info/RECORD
